fdlayout-1.0.0.dist-info/METADATA
fdlayout-1.0.0.dist-info/WHEEL
fdlayout-1.0.0.dist-info/license_files/LICENSE-APACHE
fdlayout-1.0.0.dist-info/license_files/LICENSE-MIT
fdlayout/fdlayout.pyi
fdlayout/networkx.py
fdlayout/__init__.py
fdlayout/fdlayout.cp38-win_amd64.pyd
fdlayout-1.0.0.dist-info/RECORD
